migrator.py
migrator_2000-1.0.dist-info/METADATA
migrator_2000-1.0.dist-info/RECORD
migrator_2000-1.0.dist-info/WHEEL
migrator_2000-1.0.dist-info/entry_points.txt
migrator_2000-1.0.dist-info/top_level.txt
